astrospice/__init__.py
astrospice/_version.py
astrospice/body.py
astrospice/config.py
astrospice/coords.py
astrospice/kernel.py
astrospice/net/__init__.py
astrospice/net/generic.py
astrospice/net/reg.py
astrospice/net/sources/__init__.py
astrospice/net/sources/cassini.py
astrospice/net/sources/psp.py
astrospice/net/sources/solo.py
astrospice/net/sources/stereo.py
astrospice/tests/test_body.py
astrospice/tests/test_coords.py
astrospice/tests/test_kernel.py
astrospice/tests/test_registry.py
astrospice/time/__init__.py
astrospice/time/epochs.py
astrospice-0.2.1.dist-info/LICENSE.rst
astrospice-0.2.1.dist-info/METADATA
astrospice-0.2.1.dist-info/WHEEL
astrospice-0.2.1.dist-info/top_level.txt
astrospice-0.2.1.dist-info/RECORD
