Metadata-Version: 2.1
Name: astrospice
Version: 0.2.1
Summary: A package for finding SPICE kernels and using them with astropy coordinates.
Home-page: https://astrospice.readthedocs.io/en/latest/
Author: David Stansby
Author-email: dstansby@gmail.com
License: BSD 3-Clause
Requires-Python: >=3.8
License-File: licenses/LICENSE.rst
Requires-Dist: astropy (>=5)
Requires-Dist: bs4
Requires-Dist: parfive (>=2)
Requires-Dist: spiceypy
Provides-Extra: docs
Requires-Dist: matplotlib ; extra == 'docs'
Requires-Dist: sphinx ; extra == 'docs'
Requires-Dist: sphinx-automodapi ; extra == 'docs'
Requires-Dist: sphinx-gallery ; extra == 'docs'
Requires-Dist: sphinx-rtd-theme ; extra == 'docs'
Requires-Dist: sunpy ; extra == 'docs'
Provides-Extra: test
Requires-Dist: hypothesis ; extra == 'test'
Requires-Dist: jplephem ; extra == 'test'
Requires-Dist: pytest ; extra == 'test'
Requires-Dist: pytest-doctestplus ; extra == 'test'
Requires-Dist: pytest-cov ; extra == 'test'
Requires-Dist: sunpy ; extra == 'test'
